odoo10_addon_account_payment_batch_process-10.0.1.0.1-py2.7-nspkg.pth
odoo/addons/account_payment_batch_process/README.rst
odoo/addons/account_payment_batch_process/__init__.py
odoo/addons/account_payment_batch_process/__manifest__.py
odoo/addons/account_payment_batch_process/models/__init__.py
odoo/addons/account_payment_batch_process/models/account_payment.py
odoo/addons/account_payment_batch_process/static/description/icon.png
odoo/addons/account_payment_batch_process/views/invoice_view.xml
odoo/addons/account_payment_batch_process/wizard/__init__.py
odoo/addons/account_payment_batch_process/wizard/invoice_batch_process.py
odoo/addons/account_payment_batch_process/wizard/invoice_batch_process_view.xml
odoo10_addon_account_payment_batch_process-10.0.1.0.1.dist-info/DESCRIPTION.rst
odoo10_addon_account_payment_batch_process-10.0.1.0.1.dist-info/METADATA
odoo10_addon_account_payment_batch_process-10.0.1.0.1.dist-info/RECORD
odoo10_addon_account_payment_batch_process-10.0.1.0.1.dist-info/WHEEL
odoo10_addon_account_payment_batch_process-10.0.1.0.1.dist-info/metadata.json
odoo10_addon_account_payment_batch_process-10.0.1.0.1.dist-info/namespace_packages.txt
odoo10_addon_account_payment_batch_process-10.0.1.0.1.dist-info/top_level.txt
